parle/__init__.py
parle/__main__.py
parle/errors.py
parle/plr.py
parle/random_reconciliation.py
parle/simulate.py
parle/utils.py
parle-0.0.3.dist-info/LICENSE
parle-0.0.3.dist-info/METADATA
parle-0.0.3.dist-info/WHEEL
parle-0.0.3.dist-info/top_level.txt
parle-0.0.3.dist-info/RECORD
