Metadata-Version: 2.2
Name: parle
Version: 0.0.3
Summary: PARLE: Path Analysis, Reconciliation, and Label Evaluation
Author-email: José Antonio Ramírez-Rafael <jose.ramirezra@cinvestav.mx>, Alitzel López Sánchez <alitzel.lopez.sanchez@usherbrooke.ca>, Alejandro Flores-Lamas <alejandrofloreslamas@cinvestav.mx>, Maribel Hernández-Rosales <maribel.hr@cinvestav.mx>, Manuel Lafond <manuel.lafond@usherbrooke.ca>
Project-URL: Homepage, https://gitlab.com/jarr.tecn/recondist
Project-URL: Bug Tracker, https://gitlab.com/jarr.tecn/recondist/-/issues
Keywords: tree reconciliation,gene trees,species trees,evolutionary scenarios
Classifier: Programming Language :: Python :: 3
Classifier: License :: OSI Approved :: MIT License
Classifier: Operating System :: OS Independent
Requires-Python: >=3.12
License-File: LICENSE
Requires-Dist: revolutionhtl>=1.2.0
Requires-Dist: networkx>=3.3
Requires-Dist: pandas>=2.2.2
Requires-Dist: numpy>=1.26.4
Requires-Dist: tqdm>=4.66.4
